ffmpeg_input-0.2.1.dist-info/METADATA
ffmpeg_input-0.2.1.dist-info/WHEEL
ffmpeg_input-0.2.1.dist-info/license_files/LICENSE
ffmpeg_input.libs/libsndfile-79dbb551.so.1
ffmpeg_input.libs/libcdio_cdda-92e1b2f2.so.2
ffmpeg_input.libs/libspeex-061786a2.so.1
ffmpeg_input.libs/libXi-a0a2b9be.so.6
ffmpeg_input.libs/libxcb-xfixes-a124fd6b.so.0
ffmpeg_input.libs/libtasn1-30034ce9.so.6
ffmpeg_input.libs/libsystemd-e351813f.so.0
ffmpeg_input.libs/libgpg-error-6019f251.so.0
ffmpeg_input.libs/libcom_err-4a1178d7.so.2
ffmpeg_input.libs/libpango-1-57b3fe41.0.so.0
ffmpeg_input.libs/libkrb5-4af1d28d.so.3
ffmpeg_input.libs/libjack-df8cec9f.so.0
ffmpeg_input.libs/libGLdispatch-7af6d45b.so.0
ffmpeg_input.libs/libpulsecommon-14-09cbfe09.0.so
ffmpeg_input.libs/libopenjp2-ab59a899.so.7
ffmpeg_input.libs/libavresample-aae72d7c.so.4
ffmpeg_input.libs/libmount-bbb803f3.so.1
ffmpeg_input.libs/libjpeg-55baac1c.so.62
ffmpeg_input.libs/libxcb-render-77d976b1.so.0
ffmpeg_input.libs/libuuid-8d96e403.so.1
ffmpeg_input.libs/libharfbuzz-343440fc.so.0
ffmpeg_input.libs/libxcb-8fcfc57e.so.1
ffmpeg_input.libs/libgraphite2-f18524f3.so.3
ffmpeg_input.libs/libswscale-02da309b.so.5
ffmpeg_input.libs/libpng16-1d3ada90.so.16
ffmpeg_input.libs/libX11-xcb-af9e5ce5.so.1
ffmpeg_input.libs/libfribidi-9a9ae05f.so.0
ffmpeg_input.libs/libp11-kit-7399a377.so.0
ffmpeg_input.libs/libzimg-9075c501.so.2
ffmpeg_input.libs/libcrypto-720e6dac.so.1.1
ffmpeg_input.libs/libvpx-201169cd.so.5
ffmpeg_input.libs/libv4lconvert-a8cc8f3a.so.0
ffmpeg_input.libs/libsoxr-25bd9ddc.so.0
ffmpeg_input.libs/liblz4-c89f34f6.so.1
ffmpeg_input.libs/libfreetype-8b91338f.so.6
ffmpeg_input.libs/libva-drm-8053a633.so.2
ffmpeg_input.libs/libavutil-e6fe0f55.so.56
ffmpeg_input.libs/libdbus-1-a4a23f43.so.3
ffmpeg_input.libs/libcdio_paranoia-649466e9.so.2
ffmpeg_input.libs/libpixman-1-16542a59.so.0
ffmpeg_input.libs/libgssapi_krb5-4e022f70.so.2
ffmpeg_input.libs/libssh-5abd6818.so.4
ffmpeg_input.libs/libgdk_pixbuf-2-bc7faa18.0.so.0
ffmpeg_input.libs/libogg-38327173.so.0
ffmpeg_input.libs/libtheoradec-1525d2f3.so.1
ffmpeg_input.libs/libXau-7926f62a.so.6
ffmpeg_input-0.2.1.dist-info/RECORD
