Metadata-Version: 2.1
Name: ffmpeg_input
Version: 0.2.1
Classifier: Programming Language :: Rust
Classifier: Programming Language :: Python :: Implementation :: CPython
Classifier: Programming Language :: Python :: Implementation :: PyPy
License-File: LICENSE
Summary: FFMpeg Source Accessor Library
Keywords: FFmpeg,Video
Home-Page: https://github.com/insight-platform/FFmpeg-Input
Author: Ivan Kudriavtsev <ivan.a.kudryavtsev@gmail.com>
Author-email: Ivan Kudriavtsev <ivan.a.kudryavtsev@gmail.com>
License: Apache-2.0
Requires-Python: >=3.8
Project-URL: Source Code, https://github.com/insight-platform/FFmpeg-Input
